MANIFEST.in
README.rst
setup.cfg
setup.py
Numscrypt.egg-info/PKG-INFO
Numscrypt.egg-info/SOURCES.txt
Numscrypt.egg-info/dependency_links.txt
Numscrypt.egg-info/requires.txt
Numscrypt.egg-info/top_level.txt
numscrypt/__base__.py
numscrypt/__init__.py
numscrypt/license_reference.txt
numscrypt/random.py
numscrypt/development/automated_tests/ndarray/autotest.html
numscrypt/development/automated_tests/ndarray/autotest.min.html
numscrypt/development/automated_tests/ndarray/autotest.py
numscrypt/development/automated_tests/ndarray/__javascript__/autotest.js
numscrypt/development/automated_tests/ndarray/__javascript__/autotest.min.js
numscrypt/development/automated_tests/ndarray/__javascript__/autotest.mod.js
numscrypt/development/automated_tests/ndarray/__javascript__/extra/sourcemap/autotest.js.map
numscrypt/development/automated_tests/ndarray/__javascript__/extra/sourcemap/autotest.mod.js.map
numscrypt/development/automated_tests/ndarray/basics/__init__.py
numscrypt/development/automated_tests/ndarray/basics/__javascript__/__init__.mod.js
numscrypt/development/automated_tests/ndarray/basics/__javascript__/extra/sourcemap/basics.mod.js.map
numscrypt/development/automated_tests/ndarray/module_fft/__init__.py
numscrypt/development/automated_tests/ndarray/module_fft/__javascript__/__init__.mod.js
numscrypt/development/automated_tests/ndarray/module_fft/__javascript__/extra/sourcemap/module_fft.mod.js.map
numscrypt/development/automated_tests/ndarray/module_linalg/__init__.py
numscrypt/development/automated_tests/ndarray/module_linalg/__javascript__/__init__.mod.js
numscrypt/development/automated_tests/ndarray/module_linalg/__javascript__/extra/sourcemap/module_linalg.mod.js.map
numscrypt/development/manual_tests/numpy_eig/test.html
numscrypt/development/manual_tests/numpy_eig/test.min.html
numscrypt/development/manual_tests/numpy_eig/test.py
numscrypt/development/manual_tests/numpy_eig/testmp.py
numscrypt/development/manual_tests/numpy_eig/__javascript__/test.js
numscrypt/development/manual_tests/numpy_eig/__javascript__/test.min.js
numscrypt/development/manual_tests/numpy_eig/__javascript__/test.mod.js
