Metadata-Version: 1.1
Name: Numscrypt
Version: 0.0.40
Summary: A tiny bit of NumPy for Transcrypt using JavaScript typed arrays
Home-page: https://github.com/JdeH/Numscrypt
Author: Jacques de Hooge
Author-email: jacques.de.hooge@qquick.org
License: Apache 2.0
Keywords: transcrypt,numscrypt,numpy,browser
Platform: UNKNOWN
Classifier: Development Status :: 2 - Pre-Alpha
Classifier: Intended Audience :: Developers
Classifier: Natural Language :: English
Classifier: License :: OSI Approved :: Apache Software License
Classifier: Topic :: Software Development :: Libraries :: Python Modules
Classifier: Operating System :: OS Independent
Classifier: Programming Language :: Python :: 3.5
